README.md
beancount_plugin_utils/BeancountError.py
beancount_plugin_utils/__init__.py
beancount_plugin_utils/common.py
beancount_plugin_utils/example_plugin.py
beancount_plugin_utils/marked.py
beancount_plugin_utils/merge_postings.py
beancount_plugin_utils/metaset.py
beancount_plugin_utils/parse_config_string.py
beancount_plugin_utils/test_utils.py
beancount_plugin_utils-0.0.4.dist-info/LICENSE
beancount_plugin_utils-0.0.4.dist-info/METADATA
beancount_plugin_utils-0.0.4.dist-info/WHEEL
beancount_plugin_utils-0.0.4.dist-info/top_level.txt
beancount_plugin_utils-0.0.4.dist-info/RECORD
