Metadata-Version: 2.1
Name: beancount-plugin-utils
Version: 0.0.4
Summary: Utils for beancount plugin writers - BeancountError, mark, metaset, etc.
Home-page: https://github.com/Akuukis/beancount_plugin_utils
Author: Akuukis
Author-email: akuukis@kalvis.lv
License: GNU AGPLv3
Download-URL: https://pypi.python.org/pypi/beancount_plugin_utils
Platform: UNKNOWN
Requires: beancount (>2.0)
